{
  "박주하": [
    "C:\\Users\\hyo02\\Downloads\\GitHub\\DVA\\박주하_닥터빌.bat"
  ],
  "박범준": [
    "C:\\Users\\hyo02\\Downloads\\GitHub\\DVA\\박범준_닥터빌.bat"
  ],
  "닥터빌": [
    "C:\\Users\\hyo02\\Downloads\\GitHub\\DVA\\박주하_닥터빌.bat",
    "C:\\Users\\hyo02\\Downloads\\GitHub\\DVA\\박범준_닥터빌.bat"
  ],
  "디바": [
    "C:\\Users\\hyo02\\Downloads\\GitHub\\DVA\\박주하_닥터빌.bat",
    "C:\\Users\\hyo02\\Downloads\\GitHub\\DVA\\박범준_닥터빌.bat"
  ],
  "DVA": [
    "C:\\Users\\hyo02\\Downloads\\GitHub\\DVA\\박주하_닥터빌.bat",
    "C:\\Users\\hyo02\\Downloads\\GitHub\\DVA\\박범준_닥터빌.bat"
  ],
  "ㄱㄱ": [
    "C:\\Users\\hyo02\\Downloads\\GitHub\\DVA\\박주하_닥터빌.bat",
    "C:\\Users\\hyo02\\Downloads\\GitHub\\DVA\\박범준_닥터빌.bat"
  ]
}
